{
  "name": "Region",
  "fields": [
    {
      "fieldName": "code",
      "fieldType": "String"
    },
    {
      "fieldName": "libelle",
      "fieldType": "String"
    }
  ],
  "relationships": [
    {
      "relationshipType": "one-to-many",
      "otherEntityName": "departement",
      "otherEntityRelationshipName": "region",
      "relationshipName": "departement"
    }
  ],
  "entityTableName": "region",
  "dto": "mapstruct",
  "pagination": "pagination",
  "service": "serviceImpl",
  "jpaMetamodelFiltering": true,
  "fluentMethods": true,
  "readOnly": false,
  "embedded": false,
  "applications": "*",
  "changelogDate": "20210728231140"
}
